siuba/__init__.py
siuba/meta_hook.py
siuba/data/__init__.py
siuba/data/band_instruments.csv
siuba/data/band_instruments2.csv
siuba/data/band_members.csv
siuba/data/fish_encounters.csv.gz
siuba/data/mtcars.csv.gz
siuba/data/penguins.csv.gz
siuba/data/penguins_raw.csv.gz
siuba/data/us_rent_income.csv.gz
siuba/data/warpbreaks.csv.gz
siuba/dply/__init__.py
siuba/dply/across.py
siuba/dply/forcats.py
siuba/dply/string.py
siuba/dply/tidyselect.py
siuba/dply/vector.py
siuba/dply/verbs.py
siuba/experimental/__init__.py
siuba/experimental/completer.py
siuba/experimental/datetime.py
siuba/experimental/pd_groups/__init__.py
siuba/experimental/pd_groups/dialect.py
siuba/experimental/pd_groups/groupby.py
siuba/experimental/pd_groups/test_pd_groups.py
siuba/experimental/pd_groups/translate.py
siuba/experimental/pivot/__init__.py
siuba/experimental/pivot/pivot_long.py
siuba/experimental/pivot/pivot_wide.py
siuba/experimental/pivot/sql_pivot_long.py
siuba/experimental/pivot/sql_pivot_wide.py
siuba/experimental/pivot/test_pivot.py
siuba/experimental/pivot/test_pivot_wide.py
siuba/experimental/pivot/utils.py
siuba/ops/__init__.py
siuba/ops/dt.py
siuba/ops/generics.py
siuba/ops/str.py
siuba/ops/translate.py
siuba/ops/utils.py
siuba/ops/support/__init__.py
siuba/ops/support/base.py
siuba/siu/__init__.py
siuba/siu/_databackend.py
siuba/siu/calls.py
siuba/siu/dispatchers.py
siuba/siu/error.py
siuba/siu/format.py
siuba/siu/symbolic.py
siuba/siu/utils.py
siuba/siu/visitors.py
siuba/sql/__init__.py
siuba/sql/across.py
siuba/sql/backend.py
siuba/sql/translate.py
siuba/sql/utils.py
siuba/sql/dialects/__init__.py
siuba/sql/dialects/_dt_generics.py
siuba/sql/dialects/base.py
siuba/sql/dialects/bigquery.py
siuba/sql/dialects/duckdb.py
siuba/sql/dialects/mysql.py
siuba/sql/dialects/postgresql.py
siuba/sql/dialects/redshift.py
siuba/sql/dialects/snowflake.py
siuba/sql/dialects/sqlite.py
siuba/sql/dply/__init__.py
siuba/sql/dply/string.py
siuba/sql/dply/vector.py
siuba/sql/verbs/__init__.py
siuba-0.4.4.dist-info/LICENSE
siuba-0.4.4.dist-info/METADATA
siuba-0.4.4.dist-info/WHEEL
siuba-0.4.4.dist-info/top_level.txt
siuba-0.4.4.dist-info/RECORD
