Metadata-Version: 2.1
Name: siuba
Version: 0.4.4
Summary: A package for quick, scrappy analyses with pandas and SQL
Home-page: https://github.com/machow/siuba
Author: Michael Chow
Author-email: mc_al_gh_siuba@fastmail.com
License: MIT
Keywords: package
Platform: UNKNOWN
Classifier: Programming Language :: Python :: 3
Classifier: Programming Language :: Python :: 3.7
Classifier: Programming Language :: Python :: 3.8
Classifier: Programming Language :: Python :: 3.9
Classifier: Programming Language :: Python :: 3.10
Requires-Python: >=3.7
Provides-Extra: test
Provides-Extra: docs
